youtube_talha/__init__.py
youtube_talha/downloader.py
youtube_talha-1.0.1.dist-info/METADATA
youtube_talha-1.0.1.dist-info/WHEEL
youtube_talha-1.0.1.dist-info/entry_points.txt
youtube_talha-1.0.1.dist-info/top_level.txt
youtube_talha-1.0.1.dist-info/RECORD
