Metadata-Version: 2.4
Name: youtube_talha
Version: 1.0.1
Classifier: Programming Language :: Python :: 3
Classifier: License :: OSI Approved :: MIT License
Classifier: Operating System :: OS Independent
Requires-Python: >=3.6
Requires-Dist: pytubefix
Dynamic: classifier
Dynamic: requires-dist
Dynamic: requires-python
